web_rwkv_py-0.2.3.dist-info/METADATA
web_rwkv_py-0.2.3.dist-info/WHEEL
web_rwkv_py/__init__.py
web_rwkv_py/web_rwkv_py.cpython-39-i386-linux-gnu.so
web_rwkv_py-0.2.3.dist-info/RECORD
